aliyun/instrumentation/__init__.py
aliyun/instrumentation/context/__init__.py
aliyun/instrumentation/context/context.py
aliyun/instrumentation/llama_index/__init__.py
aliyun/instrumentation/llama_index/_callback.py
aliyun/instrumentation/llama_index/_wrapper.py
aliyun/instrumentation/llama_index/package.py
aliyun/instrumentation/llama_index/version.py
aliyun/instrumentation/llama_index/internal/__init__.py
aliyun/instrumentation/llama_index/internal/_callback.py
aliyun_instrumentation_llama_index-1.0.1.dist-info/METADATA
aliyun_instrumentation_llama_index-1.0.1.dist-info/WHEEL
aliyun_instrumentation_llama_index-1.0.1.dist-info/RECORD
